<annotation>
	<folder></folder>
	<filename>40-720921-73-991053_2019-06_V3-mMHmu4YGZVgO5pMIZ_Q_d248_z2_idx2_jpg.rf.9547fd1aa220d4c8ed32d73dec6d4a8a.jpg</filename>
	<path>40-720921-73-991053_2019-06_V3-mMHmu4YGZVgO5pMIZ_Q_d248_z2_idx2_jpg.rf.9547fd1aa220d4c8ed32d73dec6d4a8a.jpg</path>
	<source>
		<database>roboflow.com</database>
	</source>
	<size>
		<width>640</width>
		<height>640</height>
		<depth>3</depth>
	</size>
	<segmented>0</segmented>
	<object>
		<name>Building</name>
		<pose>Unspecified</pose>
		<truncated>0</truncated>
		<difficult>0</difficult>
		<occluded>0</occluded>
		<bndbox>
			<xmin>1</xmin>
			<xmax>295</xmax>
			<ymin>1</ymin>
			<ymax>474</ymax>
		</bndbox>
		<polygon>
			<x1>0</x1>
			<y1>0</y1>
			<x2>0</x2>
			<y2>472.625</y2>
			<x3>2.5</x3>
			<y3>473.125</y3>
			<x4>45</x4>
			<y4>456.875</y4>
			<x5>77.5</x5>
			<y5>446.875</y5>
			<x6>80</x6>
			<y6>443.125</y6>
			<x7>122.5</x7>
			<y7>430.625</y7>
			<x8>125</x8>
			<y8>426.875</y8>
			<x9>145</x9>
			<y9>421.875</y9>
			<x10>150</x10>
			<y10>418.125</y10>
			<x11>163.75</x11>
			<y11>415.625</y11>
			<x12>167.5</x12>
			<y12>411.875</y12>
			<x13>171.25</x13>
			<y13>411.875</y13>
			<x14>176.25</x14>
			<y14>408.125</y14>
			<x15>186.25</x15>
			<y15>406.875</y15>
			<x16>191.25</x16>
			<y16>403.125</y16>
			<x17>196.25</x17>
			<y17>403.125</y17>
			<x18>207.5</x18>
			<y18>396.875</y18>
			<x19>212.5</x19>
			<y19>396.875</y19>
			<x20>228.75</x20>
			<y20>389.375</y20>
			<x21>232.5</x21>
			<y21>389.375</y21>
			<x22>233.75</x22>
			<y22>386.875</y22>
			<x23>240</x23>
			<y23>386.875</y23>
			<x24>251.25</x24>
			<y24>380.625</y24>
			<x25>260</x25>
			<y25>379.375</y25>
			<x26>262.5</x26>
			<y26>376.875</y26>
			<x27>273.75</x27>
			<y27>374.375</y27>
			<x28>278.75</x28>
			<y28>370.625</y28>
			<x29>294.375</x29>
			<y29>366.25</y29>
			<x30>293.751065</x30>
			<y30>0</y30>
			<x31>0</x31>
			<y31>0</y31>
		</polygon>
	</object>
	<object>
		<name>Building</name>
		<pose>Unspecified</pose>
		<truncated>0</truncated>
		<difficult>0</difficult>
		<occluded>0</occluded>
		<bndbox>
			<xmin>520</xmin>
			<xmax>640</xmax>
			<ymin>1</ymin>
			<ymax>402</ymax>
		</bndbox>
		<polygon>
			<x1>609.875</x1>
			<y1>0</y1>
			<x2>609.375</x2>
			<y2>2.5</y2>
			<x3>605.625</x3>
			<y3>5</y3>
			<x4>605.625</x4>
			<y4>8.75</y4>
			<x5>598.125</x5>
			<y5>15</y5>
			<x6>598.125</x6>
			<y6>18.75</y6>
			<x7>594.375</x7>
			<y7>21.25</y7>
			<x8>594.375</x8>
			<y8>25</y8>
			<x9>590.625</x9>
			<y9>27.5</y9>
			<x10>588.125</x10>
			<y10>36.25</y10>
			<x11>584.375</x11>
			<y11>38.75</y11>
			<x12>584.375</x12>
			<y12>42.5</y12>
			<x13>580.625</x13>
			<y13>45</y13>
			<x14>580.625</x14>
			<y14>48.75</y14>
			<x15>576.875</x15>
			<y15>51.25</y15>
			<x16>574.375</x16>
			<y16>58.75</y16>
			<x17>570.625</x17>
			<y17>62.5</y17>
			<x18>570.625</x18>
			<y18>67.5</y18>
			<x19>566.875</x19>
			<y19>71.25</y19>
			<x20>564.375</x20>
			<y20>78.75</y20>
			<x21>560.625</x21>
			<y21>81.25</y21>
			<x22>555.625</x22>
			<y22>90</y22>
			<x23>555.625</x23>
			<y23>95</y23>
			<x24>546.875</x24>
			<y24>106.25</y24>
			<x25>546.875</x25>
			<y25>111.25</y25>
			<x26>543.125</x26>
			<y26>113.75</y26>
			<x27>543.125</x27>
			<y27>116.25</y27>
			<x28>535.625</x28>
			<y28>126.25</y28>
			<x29>535.625</x29>
			<y29>130</y29>
			<x30>526.875</x30>
			<y30>140</y30>
			<x31>526.875</x31>
			<y31>145</y31>
			<x32>519.375</x32>
			<y32>155</y32>
			<x33>519.375</x33>
			<y33>353.75</y33>
			<x34>526.25</x34>
			<y34>355.625</y34>
			<x35>527.5</x35>
			<y35>358.125</y35>
			<x36>540</x36>
			<y36>360.625</y36>
			<x37>541.25</x37>
			<y37>363.125</y37>
			<x38>546.25</x38>
			<y38>363.125</y38>
			<x39>547.5</x39>
			<y39>365.625</y39>
			<x40>555</x40>
			<y40>366.875</y40>
			<x41>562.5</x41>
			<y41>371.875</y41>
			<x42>570</x42>
			<y42>371.875</y42>
			<x43>571.25</x43>
			<y43>374.375</y43>
			<x44>578.75</x44>
			<y44>378.125</y44>
			<x45>593.75</x45>
			<y45>381.875</y45>
			<x46>595</x46>
			<y46>384.375</y46>
			<x47>605</x47>
			<y47>385.625</y47>
			<x48>606.25</x48>
			<y48>388.125</y48>
			<x49>621.25</x49>
			<y49>393.125</y49>
			<x50>622.5</x50>
			<y50>395.625</y50>
			<x51>632.5</x51>
			<y51>396.875</y51>
			<x52>636.25</x52>
			<y52>400.625</y52>
			<x53>638.75</x53>
			<y53>400.625</y53>
			<x54>639.375</x54>
			<y54>0</y54>
			<x55>609.875</x55>
			<y55>0</y55>
		</polygon>
	</object>
	<metadata>
	</metadata>
</annotation>
