<annotation>
	<folder></folder>
	<filename>40-720151-73-996055_2019-06_bozLXN4eubuf5bWi4GWslQ_d344_z2_idx0_jpg.rf.a128276748280a5e8f93ca7d0cb70580.jpg</filename>
	<path>40-720151-73-996055_2019-06_bozLXN4eubuf5bWi4GWslQ_d344_z2_idx0_jpg.rf.a128276748280a5e8f93ca7d0cb70580.jpg</path>
	<source>
		<database>roboflow.com</database>
	</source>
	<size>
		<width>640</width>
		<height>640</height>
		<depth>3</depth>
	</size>
	<segmented>0</segmented>
	<object>
		<name>Building</name>
		<pose>Unspecified</pose>
		<truncated>0</truncated>
		<difficult>0</difficult>
		<occluded>0</occluded>
		<bndbox>
			<xmin>315</xmin>
			<xmax>593</xmax>
			<ymin>27</ymin>
			<ymax>353</ymax>
		</bndbox>
		<polygon>
			<x1>587.5</x1>
			<y1>25.625</y1>
			<x2>585</x2>
			<y2>28.125</y2>
			<x3>583.75</x3>
			<y3>25.625</y3>
			<x4>578.75</x4>
			<y4>29.375</y4>
			<x5>573.75</x5>
			<y5>25.625</y5>
			<x6>568.75</x6>
			<y6>29.375</y6>
			<x7>567.5</x7>
			<y7>26.875</y7>
			<x8>562.5</x8>
			<y8>30.625</y8>
			<x9>557.5</x9>
			<y9>26.875</y9>
			<x10>553.75</x10>
			<y10>30.625</y10>
			<x11>548.75</x11>
			<y11>26.875</y11>
			<x12>542.5</x12>
			<y12>31.875</y12>
			<x13>537.5</x13>
			<y13>28.125</y13>
			<x14>533.75</x14>
			<y14>31.875</y14>
			<x15>531.25</x15>
			<y15>29.375</y15>
			<x16>528.75</x16>
			<y16>31.875</y16>
			<x17>527.5</x17>
			<y17>29.375</y17>
			<x18>525.625</x18>
			<y18>30</y18>
			<x19>525</x19>
			<y19>26.875</y19>
			<x20>521.25</x20>
			<y20>30.625</y20>
			<x21>520</x21>
			<y21>28.125</y21>
			<x22>517.5</x22>
			<y22>29.375</y22>
			<x23>513.75</x23>
			<y23>33.125</y23>
			<x24>512.5</x24>
			<y24>30.625</y24>
			<x25>508.75</x25>
			<y25>33.125</y25>
			<x26>507.5</x26>
			<y26>30.625</y26>
			<x27>505</x27>
			<y27>31.875</y27>
			<x28>503.75</x28>
			<y28>29.375</y28>
			<x29>500</x29>
			<y29>33.125</y29>
			<x30>496.25</x30>
			<y30>28.125</y30>
			<x31>493.75</x31>
			<y31>30.625</y31>
			<x32>492.5</x32>
			<y32>28.125</y32>
			<x33>485</x33>
			<y33>34.375</y33>
			<x34>483.75</x34>
			<y34>30.625</y34>
			<x35>481.25</x35>
			<y35>33.125</y35>
			<x36>476.25</x36>
			<y36>29.375</y36>
			<x37>472.5</x37>
			<y37>33.125</y37>
			<x38>470</x38>
			<y38>30.625</y38>
			<x39>467.5</x39>
			<y39>33.125</y39>
			<x40>466.25</x40>
			<y40>30.625</y40>
			<x41>461.25</x41>
			<y41>34.375</y41>
			<x42>458.75</x42>
			<y42>31.875</y42>
			<x43>453.75</x43>
			<y43>31.875</y43>
			<x44>451.25</x44>
			<y44>34.375</y44>
			<x45>450</x45>
			<y45>31.875</y45>
			<x46>448.125</x46>
			<y46>32.5</y46>
			<x47>447.5</x47>
			<y47>29.375</y47>
			<x48>440</x48>
			<y48>35.625</y48>
			<x49>438.75</x49>
			<y49>31.875</y49>
			<x50>435</x50>
			<y50>35.625</y50>
			<x51>433.75</x51>
			<y51>31.875</y51>
			<x52>427.5</x52>
			<y52>36.875</y52>
			<x53>426.25</x53>
			<y53>34.375</y53>
			<x54>422.5</x54>
			<y54>35.625</y54>
			<x55>421.25</x55>
			<y55>33.125</y55>
			<x56>416.25</x56>
			<y56>36.875</y56>
			<x57>415</x57>
			<y57>34.375</y57>
			<x58>411.25</x58>
			<y58>35.625</y58>
			<x59>410</x59>
			<y59>33.125</y59>
			<x60>405</x60>
			<y60>36.875</y60>
			<x61>401.25</x61>
			<y61>34.375</y61>
			<x62>395</x62>
			<y62>38.125</y62>
			<x63>393.75</x63>
			<y63>35.625</y63>
			<x64>390.625</x64>
			<y64>36.25</y64>
			<x65>390</x65>
			<y65>33.125</y65>
			<x66>381.25</x66>
			<y66>38.125</y66>
			<x67>378.75</x67>
			<y67>35.625</y67>
			<x68>373.75</x68>
			<y68>36.875</y68>
			<x69>369.375</x69>
			<y69>46.25</y69>
			<x70>368.125</x70>
			<y70>56.25</y70>
			<x71>364.375</x71>
			<y71>62.5</y71>
			<x72>360.625</x72>
			<y72>81.25</y72>
			<x73>350.625</x73>
			<y73>110</y73>
			<x74>350.625</x74>
			<y74>116.25</y74>
			<x75>344.375</x75>
			<y75>130</y75>
			<x76>344.375</x76>
			<y76>136.25</y76>
			<x77>338.125</x77>
			<y77>151.25</y77>
			<x78>338.125</x78>
			<y78>157.5</y78>
			<x79>325.625</x79>
			<y79>192.5</y79>
			<x80>325.625</x80>
			<y80>200</y80>
			<x81>314.375</x81>
			<y81>232.5</y81>
			<x82>314.375</x82>
			<y82>327.5</y82>
			<x83>363.75</x83>
			<y83>348.125</y83>
			<x84>367.5</x84>
			<y84>348.125</y84>
			<x85>372.5</x85>
			<y85>351.875</y85>
			<x86>583.75</x86>
			<y86>351.875</y86>
			<x87>588.125</x87>
			<y87>350</y87>
			<x88>588.125</x88>
			<y88>112.5</y88>
			<x89>591.875</x89>
			<y89>108.75</y89>
			<x90>591.875</x90>
			<y90>27.5</y90>
			<x91>588.75</x91>
			<y91>29.375</y91>
			<x92>587.5</x92>
			<y92>25.625</y92>
		</polygon>
	</object>
	<object>
		<name>Building</name>
		<pose>Unspecified</pose>
		<truncated>0</truncated>
		<difficult>0</difficult>
		<occluded>0</occluded>
		<bndbox>
			<xmin>1</xmin>
			<xmax>259</xmax>
			<ymin>104</ymin>
			<ymax>348</ymax>
		</bndbox>
		<polygon>
			<x1>0</x1>
			<y1>342.625</y1>
			<x2>8.75</x2>
			<y2>344.375</y2>
			<x3>38.75</x3>
			<y3>343.125</y3>
			<x4>40</x4>
			<y4>345.625</y4>
			<x5>63.75</x5>
			<y5>343.125</y5>
			<x6>65</x6>
			<y6>345.625</y6>
			<x7>192.5</x7>
			<y7>344.375</y7>
			<x8>212.5</x8>
			<y8>346.875</y8>
			<x9>221.25</x9>
			<y9>341.875</y9>
			<x10>233.75</x10>
			<y10>339.375</y10>
			<x11>236.25</x11>
			<y11>336.875</y11>
			<x12>258.125</x12>
			<y12>328.75</y12>
			<x13>258.125</x13>
			<y13>235</y13>
			<x14>213.125</x14>
			<y14>102.5</y14>
			<x15>211.25</x15>
			<y15>111.875</y15>
			<x16>206.25</x16>
			<y16>109.375</y16>
			<x17>202.5</x17>
			<y17>113.125</y17>
			<x18>198.75</x18>
			<y18>110.625</y18>
			<x19>187.5</x19>
			<y19>113.125</y19>
			<x20>183.75</x20>
			<y20>110.625</y20>
			<x21>178.75</x21>
			<y21>113.125</y21>
			<x22>173.75</x22>
			<y22>110.625</y22>
			<x23>166.25</x23>
			<y23>114.375</y23>
			<x24>161.25</x24>
			<y24>110.625</y24>
			<x25>157.5</x25>
			<y25>114.375</y25>
			<x26>152.5</x26>
			<y26>114.375</y26>
			<x27>148.75</x27>
			<y27>111.875</y27>
			<x28>147.5</x28>
			<y28>114.375</y28>
			<x29>145</x29>
			<y29>111.875</y29>
			<x30>143.75</x30>
			<y30>114.375</y30>
			<x31>137.5</x31>
			<y31>110.625</y31>
			<x32>135</x32>
			<y32>114.375</y32>
			<x33>131.25</x33>
			<y33>111.875</y33>
			<x34>130</x34>
			<y34>114.375</y34>
			<x35>126.25</x35>
			<y35>111.875</y35>
			<x36>125</x36>
			<y36>114.375</y36>
			<x37>121.25</x37>
			<y37>111.875</y37>
			<x38>120</x38>
			<y38>114.375</y38>
			<x39>116.25</x39>
			<y39>111.875</y39>
			<x40>112.5</x40>
			<y40>115.625</y40>
			<x41>108.75</x41>
			<y41>113.125</y41>
			<x42>107.5</x42>
			<y42>115.625</y42>
			<x43>103.75</x43>
			<y43>113.125</y43>
			<x44>98.75</x44>
			<y44>115.625</y44>
			<x45>92.5</x45>
			<y45>111.875</y45>
			<x46>88.75</x46>
			<y46>115.625</y46>
			<x47>83.75</x47>
			<y47>113.125</y47>
			<x48>78.75</x48>
			<y48>115.625</y48>
			<x49>75</x49>
			<y49>113.125</y49>
			<x50>73.75</x50>
			<y50>115.625</y50>
			<x51>68.75</x51>
			<y51>115.625</y51>
			<x52>65</x52>
			<y52>113.125</y52>
			<x53>60</x53>
			<y53>116.875</y53>
			<x54>56.25</x54>
			<y54>114.375</y54>
			<x55>52.5</x55>
			<y55>115.625</y55>
			<x56>47.5</x56>
			<y56>113.125</y56>
			<x57>46.25</x57>
			<y57>118.125</y57>
			<x58>40</x58>
			<y58>114.375</y58>
			<x59>38.75</x59>
			<y59>116.875</y59>
			<x60>32.5</x60>
			<y60>113.125</y60>
			<x61>27.5</x61>
			<y61>116.875</y61>
			<x62>25</x62>
			<y62>115.625</y62>
			<x63>23.75</x63>
			<y63>118.125</y63>
			<x64>17.5</x64>
			<y64>114.375</y64>
			<x65>15</x65>
			<y65>116.875</y65>
			<x66>10</x66>
			<y66>116.875</y66>
			<x67>3.75</x67>
			<y67>114.375</y67>
			<x68>2.5</x68>
			<y68>119.375</y68>
			<x69>0</x69>
			<y69>118.875</y69>
			<x70>0</x70>
			<y70>342.625</y70>
		</polygon>
	</object>
	<object>
		<name>Building</name>
		<pose>Unspecified</pose>
		<truncated>0</truncated>
		<difficult>0</difficult>
		<occluded>0</occluded>
		<bndbox>
			<xmin>597</xmin>
			<xmax>640</xmax>
			<ymin>112</ymin>
			<ymax>353</ymax>
		</bndbox>
		<polygon>
			<x1>628.75</x1>
			<y1>114.375</y1>
			<x2>626.25</x2>
			<y2>111.875</y2>
			<x3>623.75</x3>
			<y3>113.125</y3>
			<x4>622.5</x4>
			<y4>110.625</y4>
			<x5>616.25</x5>
			<y5>114.375</y5>
			<x6>611.25</x6>
			<y6>114.375</y6>
			<x7>608.75</x7>
			<y7>111.875</y7>
			<x8>600</x8>
			<y8>116.875</y8>
			<x9>598.75</x9>
			<y9>114.375</y9>
			<x10>595.625</x10>
			<y10>116.25</y10>
			<x11>595.625</x11>
			<y11>348.75</y11>
			<x12>626.25</x12>
			<y12>351.875</y12>
			<x13>627.5</x13>
			<y13>349.375</y13>
			<x14>639.375</x14>
			<y14>348.75</y14>
			<x15>639.375</x15>
			<y15>112.5</y15>
			<x16>636.25</x16>
			<y16>113.125</y16>
			<x17>635</x17>
			<y17>110.625</y17>
			<x18>628.75</x18>
			<y18>114.375</y18>
		</polygon>
	</object>
	<metadata>
	</metadata>
</annotation>
