<annotation>
	<folder></folder>
	<filename>40-721067-73-984057_2019-06_nk_QoCWi2wK1PlpMZ1MQeA_d159_z2_idx1_jpg.rf.7ea9f3a19420a4bec3eea252930732d6.jpg</filename>
	<path>40-721067-73-984057_2019-06_nk_QoCWi2wK1PlpMZ1MQeA_d159_z2_idx1_jpg.rf.7ea9f3a19420a4bec3eea252930732d6.jpg</path>
	<source>
		<database>roboflow.com</database>
	</source>
	<size>
		<width>640</width>
		<height>640</height>
		<depth>3</depth>
	</size>
	<segmented>0</segmented>
	<object>
		<name>Building</name>
		<pose>Unspecified</pose>
		<truncated>0</truncated>
		<difficult>0</difficult>
		<occluded>0</occluded>
		<bndbox>
			<xmin>1</xmin>
			<xmax>233</xmax>
			<ymin>1</ymin>
			<ymax>417</ymax>
		</bndbox>
		<polygon>
			<x1>0</x1>
			<y1>0</y1>
			<x2>0</x2>
			<y2>415.208334</y2>
			<x3>1.25</x3>
			<y3>415.625</y3>
			<x4>11.25</x4>
			<y4>413.125</y4>
			<x5>13.75</x5>
			<y5>409.375</y5>
			<x6>23.75</x6>
			<y6>408.125</y6>
			<x7>26.25</x7>
			<y7>404.375</y7>
			<x8>50</x8>
			<y8>400.625</y8>
			<x9>52.5</x9>
			<y9>396.875</y9>
			<x10>57.5</x10>
			<y10>396.875</y10>
			<x11>62.5</x11>
			<y11>393.125</y11>
			<x12>73.75</x12>
			<y12>391.875</y12>
			<x13>77.5</x13>
			<y13>388.125</y13>
			<x14>83.75</x14>
			<y14>388.125</y14>
			<x15>87.5</x15>
			<y15>384.375</y15>
			<x16>100</x16>
			<y16>383.125</y16>
			<x17>101.25</x17>
			<y17>380.625</y17>
			<x18>105</x18>
			<y18>380.625</y18>
			<x19>111.25</x19>
			<y19>376.875</y19>
			<x20>117.5</x20>
			<y20>376.875</y20>
			<x21>123.75</x21>
			<y21>371.875</y21>
			<x22>141.25</x22>
			<y22>368.125</y22>
			<x23>142.5</x23>
			<y23>365.625</y23>
			<x24>150</x24>
			<y24>365.625</y24>
			<x25>151.25</x25>
			<y25>363.125</y25>
			<x26>156.25</x26>
			<y26>363.125</y26>
			<x27>157.5</x27>
			<y27>360.625</y27>
			<x28>171.25</x28>
			<y28>358.125</y28>
			<x29>176.25</x29>
			<y29>354.375</y29>
			<x30>182.5</x30>
			<y30>354.375</y30>
			<x31>198.75</x31>
			<y31>346.875</y31>
			<x32>203.75</x32>
			<y32>346.875</y32>
			<x33>231.875</x33>
			<y33>336.25</y33>
			<x34>231.875</x34>
			<y34>217.5</y34>
			<x35>224.375</x35>
			<y35>201.25</y35>
			<x36>221.875</x36>
			<y36>200</y36>
			<x37>218.125</x37>
			<y37>188.75</y37>
			<x38>213.125</x38>
			<y38>183.75</y38>
			<x39>210.625</x39>
			<y39>173.75</y39>
			<x40>205.625</x40>
			<y40>167.5</y40>
			<x41>203.125</x41>
			<y41>158.75</y41>
			<x42>200.625</x42>
			<y42>157.5</y42>
			<x43>188.125</x43>
			<y43>132.5</y43>
			<x44>185.625</x44>
			<y44>131.25</y44>
			<x45>185.625</x45>
			<y45>126.25</y45>
			<x46>179.375</x46>
			<y46>113.75</y46>
			<x47>175.625</x47>
			<y47>111.25</y47>
			<x48>174.375</x48>
			<y48>102.5</y48>
			<x49>168.125</x49>
			<y49>96.25</y49>
			<x50>166.875</x50>
			<y50>87.5</y50>
			<x51>161.875</x51>
			<y51>83.75</y51>
			<x52>160.625</x52>
			<y52>77.5</y52>
			<x53>156.875</x53>
			<y53>75</y53>
			<x54>156.875</x54>
			<y54>68.75</y54>
			<x55>151.875</x55>
			<y55>65</y55>
			<x56>150.625</x56>
			<y56>55</y56>
			<x57>145.625</x57>
			<y57>51.25</y57>
			<x58>141.875</x58>
			<y58>42.5</y58>
			<x59>136.875</x59>
			<y59>37.5</y59>
			<x60>136.875</x60>
			<y60>31.25</y60>
			<x61>133.125</x61>
			<y61>28.75</y61>
			<x62>133.125</x62>
			<y62>25</y62>
			<x63>128.125</x63>
			<y63>21.25</y63>
			<x64>128.125</x64>
			<y64>13.75</y64>
			<x65>117.961956</x65>
			<y65>0</y65>
			<x66>0</x66>
			<y66>0</y66>
		</polygon>
	</object>
	<object>
		<name>Building</name>
		<pose>Unspecified</pose>
		<truncated>0</truncated>
		<difficult>0</difficult>
		<occluded>0</occluded>
		<bndbox>
			<xmin>417</xmin>
			<xmax>640</xmax>
			<ymin>1</ymin>
			<ymax>427</ymax>
		</bndbox>
		<polygon>
			<x1>426.201923</x1>
			<y1>0</y1>
			<x2>425.625</x2>
			<y2>7.5</y2>
			<x3>421.875</x3>
			<y3>10</y3>
			<x4>421.875</x4>
			<y4>13.75</y4>
			<x5>418.125</x5>
			<y5>16.25</y5>
			<x6>418.125</x6>
			<y6>20</y6>
			<x7>415.625</x7>
			<y7>22.5</y7>
			<x8>415.625</x8>
			<y8>356.25</y8>
			<x9>418.75</x9>
			<y9>359.375</y9>
			<x10>425</x10>
			<y10>359.375</y10>
			<x11>432.5</x11>
			<y11>363.125</y11>
			<x12>437.5</x12>
			<y12>363.125</y12>
			<x13>440</x13>
			<y13>365.625</y13>
			<x14>447.5</x14>
			<y14>365.625</y14>
			<x15>448.75</x15>
			<y15>368.125</y15>
			<x16>452.5</x16>
			<y16>368.125</y16>
			<x17>455</x17>
			<y17>370.625</y17>
			<x18>462.5</x18>
			<y18>370.625</y18>
			<x19>463.75</x19>
			<y19>373.125</y19>
			<x20>470</x20>
			<y20>373.125</y20>
			<x21>483.75</x21>
			<y21>379.375</y21>
			<x22>495</x22>
			<y22>380.625</y22>
			<x23>496.25</x23>
			<y23>383.125</y23>
			<x24>510</x24>
			<y24>384.375</y24>
			<x25>511.25</x25>
			<y25>386.875</y25>
			<x26>520</x26>
			<y26>388.125</y26>
			<x27>525</x27>
			<y27>391.875</y27>
			<x28>537.5</x28>
			<y28>393.125</y28>
			<x29>542.5</x29>
			<y29>396.875</y29>
			<x30>563.75</x30>
			<y30>400.625</y30>
			<x31>567.5</x31>
			<y31>404.375</y31>
			<x32>593.75</x32>
			<y32>409.375</y32>
			<x33>596.25</x33>
			<y33>413.125</y33>
			<x34>627.5</x34>
			<y34>419.375</y34>
			<x35>631.25</x35>
			<y35>420.625</y35>
			<x36>633.75</x36>
			<y36>424.375</y36>
			<x37>638.75</x37>
			<y37>425.625</y37>
			<x38>639.375</x38>
			<y38>0</y38>
			<x39>426.201923</x39>
			<y39>0</y39>
		</polygon>
	</object>
	<metadata>
	</metadata>
</annotation>
