<annotation>
	<folder></folder>
	<filename>car15_png.rf.6d8ad220573ad4d8c4af50032988911a.jpg</filename>
	<path>car15_png.rf.6d8ad220573ad4d8c4af50032988911a.jpg</path>
	<source>
		<database>roboflow.com</database>
	</source>
	<size>
		<width>640</width>
		<height>417</height>
		<depth>3</depth>
	</size>
	<segmented>0</segmented>
	<object>
		<name>car</name>
		<pose>Unspecified</pose>
		<truncated>0</truncated>
		<difficult>0</difficult>
		<occluded>0</occluded>
		<bndbox>
			<xmin>78</xmin>
			<xmax>549</xmax>
			<ymin>85</ymin>
			<ymax>364</ymax>
		</bndbox>
	</object>
	<object>
		<name>License_Plate</name>
		<pose>Unspecified</pose>
		<truncated>0</truncated>
		<difficult>0</difficult>
		<occluded>0</occluded>
		<bndbox>
			<xmin>375</xmin>
			<xmax>461</xmax>
			<ymin>255</ymin>
			<ymax>286</ymax>
		</bndbox>
	</object>
	<metadata>
	</metadata>
</annotation>
