<annotation>
	<folder></folder>
	<filename>20250517_180637_jpg.rf.d606d9f9ed54ceda3870dab315717d47.jpg</filename>
	<path>20250517_180637_jpg.rf.d606d9f9ed54ceda3870dab315717d47.jpg</path>
	<source>
		<database>roboflow.com</database>
	</source>
	<size>
		<width>360</width>
		<height>640</height>
		<depth>3</depth>
	</size>
	<segmented>0</segmented>
	<object>
		<name>License_Plate</name>
		<pose>Unspecified</pose>
		<truncated>0</truncated>
		<difficult>0</difficult>
		<occluded>0</occluded>
		<bndbox>
			<xmin>96</xmin>
			<xmax>157</xmax>
			<ymin>389</ymin>
			<ymax>426</ymax>
		</bndbox>
	</object>
	<object>
		<name>car</name>
		<pose>Unspecified</pose>
		<truncated>0</truncated>
		<difficult>0</difficult>
		<occluded>0</occluded>
		<bndbox>
			<xmin>2</xmin>
			<xmax>129</xmax>
			<ymin>205</ymin>
			<ymax>377</ymax>
		</bndbox>
	</object>
	<object>
		<name>car</name>
		<pose>Unspecified</pose>
		<truncated>0</truncated>
		<difficult>0</difficult>
		<occluded>0</occluded>
		<bndbox>
			<xmin>34</xmin>
			<xmax>325</xmax>
			<ymin>225</ymin>
			<ymax>441</ymax>
		</bndbox>
	</object>
	<object>
		<name>car</name>
		<pose>Unspecified</pose>
		<truncated>0</truncated>
		<difficult>0</difficult>
		<occluded>0</occluded>
		<bndbox>
			<xmin>304</xmin>
			<xmax>361</xmax>
			<ymin>215</ymin>
			<ymax>289</ymax>
		</bndbox>
	</object>
	<metadata>
	</metadata>
</annotation>
