<annotation>
	<folder></folder>
	<filename>20250518_184731_jpg.rf.7c0f5af8033999a97474681a704e75fe.jpg</filename>
	<path>20250518_184731_jpg.rf.7c0f5af8033999a97474681a704e75fe.jpg</path>
	<source>
		<database>roboflow.com</database>
	</source>
	<size>
		<width>360</width>
		<height>640</height>
		<depth>3</depth>
	</size>
	<segmented>0</segmented>
	<object>
		<name>License_Plate</name>
		<pose>Unspecified</pose>
		<truncated>0</truncated>
		<difficult>0</difficult>
		<occluded>0</occluded>
		<bndbox>
			<xmin>137</xmin>
			<xmax>198</xmax>
			<ymin>392</ymin>
			<ymax>433</ymax>
		</bndbox>
	</object>
	<object>
		<name>car</name>
		<pose>Unspecified</pose>
		<truncated>0</truncated>
		<difficult>0</difficult>
		<occluded>0</occluded>
		<bndbox>
			<xmin>23</xmin>
			<xmax>317</xmax>
			<ymin>195</ymin>
			<ymax>470</ymax>
		</bndbox>
	</object>
	<metadata>
	</metadata>
</annotation>
