<annotation>
	<folder></folder>
	<filename>20250518_184409_jpg.rf.358c2b665c1a9822e0a3ccc6a5b526fb.jpg</filename>
	<path>20250518_184409_jpg.rf.358c2b665c1a9822e0a3ccc6a5b526fb.jpg</path>
	<source>
		<database>roboflow.com</database>
	</source>
	<size>
		<width>360</width>
		<height>640</height>
		<depth>3</depth>
	</size>
	<segmented>0</segmented>
	<object>
		<name>License_Plate</name>
		<pose>Unspecified</pose>
		<truncated>0</truncated>
		<difficult>0</difficult>
		<occluded>0</occluded>
		<bndbox>
			<xmin>83</xmin>
			<xmax>251</xmax>
			<ymin>313</ymin>
			<ymax>390</ymax>
		</bndbox>
	</object>
	<object>
		<name>car</name>
		<pose>Unspecified</pose>
		<truncated>0</truncated>
		<difficult>0</difficult>
		<occluded>0</occluded>
		<bndbox>
			<xmin>1</xmin>
			<xmax>343</xmax>
			<ymin>166</ymin>
			<ymax>485</ymax>
		</bndbox>
	</object>
	<metadata>
	</metadata>
</annotation>
