<annotation>
	<folder></folder>
	<filename>347399066_3338889583088080_8403640752024460767_n_jpg.rf.15efbdd2b380758eca5adbdc643b4b6a.jpg</filename>
	<path>347399066_3338889583088080_8403640752024460767_n_jpg.rf.15efbdd2b380758eca5adbdc643b4b6a.jpg</path>
	<source>
		<database>roboflow.com</database>
	</source>
	<size>
		<width>480</width>
		<height>640</height>
		<depth>3</depth>
	</size>
	<segmented>0</segmented>
	<object>
		<name>License_Plate</name>
		<pose>Unspecified</pose>
		<truncated>0</truncated>
		<difficult>0</difficult>
		<occluded>0</occluded>
		<bndbox>
			<xmin>191</xmin>
			<xmax>324</xmax>
			<ymin>361</ymin>
			<ymax>421</ymax>
		</bndbox>
	</object>
	<object>
		<name>car</name>
		<pose>Unspecified</pose>
		<truncated>0</truncated>
		<difficult>0</difficult>
		<occluded>0</occluded>
		<bndbox>
			<xmin>50</xmin>
			<xmax>479</xmax>
			<ymin>182</ymin>
			<ymax>569</ymax>
		</bndbox>
	</object>
	<metadata>
	</metadata>
</annotation>
