<annotation>
	<folder></folder>
	<filename>352221346_10230713015956907_307626554500962384_n-1-_jpg.rf.456e2d5b71bd195dd0a4ee9dbd088bcf.jpg</filename>
	<path>352221346_10230713015956907_307626554500962384_n-1-_jpg.rf.456e2d5b71bd195dd0a4ee9dbd088bcf.jpg</path>
	<source>
		<database>roboflow.com</database>
	</source>
	<size>
		<width>480</width>
		<height>640</height>
		<depth>3</depth>
	</size>
	<segmented>0</segmented>
	<object>
		<name>License_Plate</name>
		<pose>Unspecified</pose>
		<truncated>0</truncated>
		<difficult>0</difficult>
		<occluded>0</occluded>
		<bndbox>
			<xmin>173</xmin>
			<xmax>298</xmax>
			<ymin>375</ymin>
			<ymax>411</ymax>
		</bndbox>
	</object>
	<object>
		<name>car</name>
		<pose>Unspecified</pose>
		<truncated>0</truncated>
		<difficult>0</difficult>
		<occluded>0</occluded>
		<bndbox>
			<xmin>24</xmin>
			<xmax>444</xmax>
			<ymin>183</ymin>
			<ymax>526</ymax>
		</bndbox>
	</object>
	<metadata>
	</metadata>
</annotation>
