<annotation>
	<folder></folder>
	<filename>40-726329-73-993478_2019-06_nEMGG2ARHWrKPyttTvuwKQ_d60_z2_idx0_jpg.rf.65cb896f63921be6b49a146439b81dd3.jpg</filename>
	<path>40-726329-73-993478_2019-06_nEMGG2ARHWrKPyttTvuwKQ_d60_z2_idx0_jpg.rf.65cb896f63921be6b49a146439b81dd3.jpg</path>
	<source>
		<database>roboflow.com</database>
	</source>
	<size>
		<width>640</width>
		<height>640</height>
		<depth>3</depth>
	</size>
	<segmented>0</segmented>
	<object>
		<name>Building</name>
		<pose>Unspecified</pose>
		<truncated>0</truncated>
		<difficult>0</difficult>
		<occluded>0</occluded>
		<bndbox>
			<xmin>1</xmin>
			<xmax>229</xmax>
			<ymin>1</ymin>
			<ymax>380</ymax>
		</bndbox>
		<polygon>
			<x1>0</x1>
			<y1>0</y1>
			<x2>0</x2>
			<y2>378.798077</y2>
			<x3>7.5</x3>
			<y3>379.375</y3>
			<x4>15</x4>
			<y4>378.125</y4>
			<x5>20</x5>
			<y5>374.375</y5>
			<x6>37.5</x6>
			<y6>373.125</y6>
			<x7>41.25</x7>
			<y7>369.375</y7>
			<x8>60</x8>
			<y8>368.125</y8>
			<x9>66.25</x9>
			<y9>364.375</y9>
			<x10>82.5</x10>
			<y10>363.125</y10>
			<x11>83.75</x11>
			<y11>360.625</y11>
			<x12>103.75</x12>
			<y12>359.375</y12>
			<x13>106.25</x13>
			<y13>356.875</y13>
			<x14>117.5</x14>
			<y14>355.625</y14>
			<x15>120</x15>
			<y15>353.125</y15>
			<x16>132.5</x16>
			<y16>353.125</y16>
			<x17>136.25</x17>
			<y17>350.625</y17>
			<x18>155</x18>
			<y18>348.125</y18>
			<x19>158.75</x19>
			<y19>345.625</y19>
			<x20>167.5</x20>
			<y20>345.625</y20>
			<x21>168.75</x21>
			<y21>343.125</y21>
			<x22>178.75</x22>
			<y22>343.125</y22>
			<x23>183.75</x23>
			<y23>340.625</y23>
			<x24>202.5</x24>
			<y24>338.125</y24>
			<x25>205</x25>
			<y25>335.625</y25>
			<x26>226.25</x26>
			<y26>333.125</y26>
			<x27>228.125</x27>
			<y27>331.25</y27>
			<x28>228.125</x28>
			<y28>180</y28>
			<x29>224.375</x29>
			<y29>172.5</y29>
			<x30>221.875</x30>
			<y30>171.25</y30>
			<x31>215.625</x31>
			<y31>151.25</y31>
			<x32>213.125</x32>
			<y32>150</y32>
			<x33>209.375</x33>
			<y33>140</y33>
			<x34>206.875</x34>
			<y34>138.75</y34>
			<x35>199.375</x35>
			<y35>123.75</y35>
			<x36>196.875</x36>
			<y36>112.5</y36>
			<x37>194.375</x37>
			<y37>111.25</y37>
			<x38>191.875</x38>
			<y38>102.5</y38>
			<x39>185.625</x39>
			<y39>95</y39>
			<x40>184.375</x40>
			<y40>86.25</y40>
			<x41>176.875</x41>
			<y41>76.25</y41>
			<x42>175.625</x42>
			<y42>66.25</y42>
			<x43>168.125</x43>
			<y43>57.5</y43>
			<x44>166.875</x44>
			<y44>47.5</y44>
			<x45>161.875</x45>
			<y45>43.75</y45>
			<x46>161.875</x46>
			<y46>40</y46>
			<x47>158.125</x47>
			<y47>37.5</y47>
			<x48>156.875</x48>
			<y48>25</y48>
			<x49>151.875</x49>
			<y49>21.25</y49>
			<x50>151.875</x50>
			<y50>17.5</y50>
			<x51>148.125</x51>
			<y51>15</y51>
			<x52>148.125</x52>
			<y52>7.5</y52>
			<x53>144.375</x53>
			<y53>3.75</y53>
			<x54>143.839286</x54>
			<y54>0</y54>
			<x55>0</x55>
			<y55>0</y55>
		</polygon>
	</object>
	<object>
		<name>Building</name>
		<pose>Unspecified</pose>
		<truncated>0</truncated>
		<difficult>0</difficult>
		<occluded>0</occluded>
		<bndbox>
			<xmin>429</xmin>
			<xmax>597</xmax>
			<ymin>1</ymin>
			<ymax>395</ymax>
		</bndbox>
		<polygon>
			<x1>441.041666</x1>
			<y1>0</y1>
			<x2>439.375</x2>
			<y2>5</y2>
			<x3>435.625</x3>
			<y3>7.5</y3>
			<x4>431.875</x4>
			<y4>22.5</y4>
			<x5>428.125</x5>
			<y5>25</y5>
			<x6>428.125</x6>
			<y6>350</y6>
			<x7>435</x7>
			<y7>351.875</y7>
			<x8>436.25</x8>
			<y8>354.375</y8>
			<x9>443.75</x9>
			<y9>354.375</y9>
			<x10>471.25</x10>
			<y10>363.125</y10>
			<x11>483.75</x11>
			<y11>364.375</y11>
			<x12>485</x12>
			<y12>366.875</y12>
			<x13>493.75</x13>
			<y13>366.875</y13>
			<x14>496.25</x14>
			<y14>369.375</y14>
			<x15>507.5</x15>
			<y15>370.625</y15>
			<x16>508.75</x16>
			<y16>373.125</y16>
			<x17>522.5</x17>
			<y17>374.375</y17>
			<x18>523.75</x18>
			<y18>376.875</y18>
			<x19>528.75</x19>
			<y19>378.125</y19>
			<x20>536.25</x20>
			<y20>378.125</y20>
			<x21>541.25</x21>
			<y21>381.875</y21>
			<x22>555</x22>
			<y22>383.125</y22>
			<x23>558.75</x23>
			<y23>386.875</y23>
			<x24>572.5</x24>
			<y24>388.125</y24>
			<x25>582.5</x25>
			<y25>393.125</y25>
			<x26>595</x26>
			<y26>394.375</y26>
			<x27>595.625</x27>
			<y27>0</y27>
			<x28>441.041666</x28>
			<y28>0</y28>
		</polygon>
	</object>
	<object>
		<name>Building</name>
		<pose>Unspecified</pose>
		<truncated>0</truncated>
		<difficult>0</difficult>
		<occluded>0</occluded>
		<bndbox>
			<xmin>382</xmin>
			<xmax>426</xmax>
			<ymin>132</ymin>
			<ymax>352</ymax>
		</bndbox>
		<polygon>
			<x1>399.375</x1>
			<y1>167.5</y1>
			<x2>388.125</x2>
			<y2>188.75</y2>
			<x3>380.625</x3>
			<y3>198.75</y3>
			<x4>380.625</x4>
			<y4>337.5</y4>
			<x5>382.5</x5>
			<y5>339.375</y5>
			<x6>402.5</x6>
			<y6>343.125</y6>
			<x7>405</x7>
			<y7>345.625</y7>
			<x8>422.5</x8>
			<y8>348.125</y8>
			<x9>425</x9>
			<y9>350.625</y9>
			<x10>425</x10>
			<y10>130.625</y10>
			<x11>420.625</x11>
			<y11>135</y11>
			<x12>415.625</x12>
			<y12>147.5</y12>
			<x13>408.125</x13>
			<y13>155</y13>
			<x14>403.125</x14>
			<y14>166.25</y14>
			<x15>399.375</x15>
			<y15>167.5</y15>
		</polygon>
	</object>
	<object>
		<name>Building</name>
		<pose>Unspecified</pose>
		<truncated>0</truncated>
		<difficult>0</difficult>
		<occluded>0</occluded>
		<bndbox>
			<xmin>604</xmin>
			<xmax>640</xmax>
			<ymin>1</ymin>
			<ymax>407</ymax>
		</bndbox>
		<polygon>
			<x1>603.749023</x1>
			<y1>0</y1>
			<x2>603.125</x2>
			<y2>398.75</y2>
			<x3>638.75</x3>
			<y3>405.625</y3>
			<x4>639.375</x4>
			<y4>0</y4>
			<x5>603.749023</x5>
			<y5>0</y5>
		</polygon>
	</object>
	<metadata>
	</metadata>
</annotation>
